s3pipe/__init__.py
s3pipe/models/__init__.py
s3pipe/models/layers.py
s3pipe/models/models.py
s3pipe/models/unet3d.py
s3pipe/surface/__init__.py
s3pipe/surface/atlas.py
s3pipe/surface/inflate.py
s3pipe/surface/parc.py
s3pipe/surface/prop.py
s3pipe/surface/s3map.py
s3pipe/surface/s3reg.py
s3pipe/surface/surf.py
s3pipe/surface/surf_jit.py
s3pipe/utils/__init__.py
s3pipe/utils/image.py
s3pipe/utils/interp_numpy.py
s3pipe/utils/interp_torch.py
s3pipe/utils/utils.py
s3pipe/utils/vtk.py
s3pipe/utils/neigh_indices/FScolortable.txt
s3pipe/utils/neigh_indices/ROI_36_TO_NAMIC35.txt
s3pipe/utils/neigh_indices/adj_mat_order_10242_rotated_0.npy
s3pipe/utils/neigh_indices/adj_mat_order_10242_rotated_1.npy
s3pipe/utils/neigh_indices/adj_mat_order_10242_rotated_2.npy
s3pipe/utils/neigh_indices/adj_mat_order_12_rotated_0.npy
s3pipe/utils/neigh_indices/adj_mat_order_12_rotated_1.npy
s3pipe/utils/neigh_indices/adj_mat_order_12_rotated_2.npy
s3pipe/utils/neigh_indices/adj_mat_order_162_rotated_0.npy
s3pipe/utils/neigh_indices/adj_mat_order_162_rotated_1.npy
s3pipe/utils/neigh_indices/adj_mat_order_162_rotated_2.npy
s3pipe/utils/neigh_indices/adj_mat_order_163842_rotated_0.npy
s3pipe/utils/neigh_indices/adj_mat_order_163842_rotated_1.npy
s3pipe/utils/neigh_indices/adj_mat_order_163842_rotated_2.npy
s3pipe/utils/neigh_indices/adj_mat_order_2562_rotated_0.npy
s3pipe/utils/neigh_indices/adj_mat_order_2562_rotated_1.npy
s3pipe/utils/neigh_indices/adj_mat_order_2562_rotated_2.npy
s3pipe/utils/neigh_indices/adj_mat_order_40962_rotated_0.npy
s3pipe/utils/neigh_indices/adj_mat_order_40962_rotated_1.npy
s3pipe/utils/neigh_indices/adj_mat_order_40962_rotated_2.npy
s3pipe/utils/neigh_indices/adj_mat_order_42_rotated_0.npy
s3pipe/utils/neigh_indices/adj_mat_order_42_rotated_1.npy
s3pipe/utils/neigh_indices/adj_mat_order_42_rotated_2.npy
s3pipe/utils/neigh_indices/adj_mat_order_642_rotated_0.npy
s3pipe/utils/neigh_indices/adj_mat_order_642_rotated_1.npy
s3pipe-1.3.0.dist-info/LICENSE
s3pipe-1.3.0.dist-info/METADATA
s3pipe-1.3.0.dist-info/WHEEL
s3pipe-1.3.0.dist-info/top_level.txt
s3pipe-1.3.0.dist-info/RECORD
