Metadata-Version: 2.1
Name: s3pipe
Version: 1.3.0
Summary: This is a pipeline for superfast spherical surface processing
Home-page: https://github.com/BRAIN-Lab-UNC/s3pipe
Author: Fenqiang Zhao
Author-email: zhaofenqiang0221@gmail.com
License: CC BY-NC-SA 4.0
Requires-Python: >=3.9
License-File: LICENSE
Requires-Dist: numpy
Requires-Dist: scipy
